{
    "name": "GeoCoin",
    "symbol": "GEO",
    "source": "cyberFund",
    "metrics": {
        "announce": "18/08/2013",
        "genesis": "12/08/2013",
        "status": "Dead",
        "p2p": 3990,
        "rpc": 3991,
        "blockTime": null,
        "reward": 33,
        "halfingCycle": null,
        "total": 1000000000,
        "premine": 25000000,
        "difficultyCycle": "20",
        "txsConfirm": null,
        "mintConfirm": 25,
        "ann": "https://bitcointalk.org/index.php?topic=277091.0",
        "algo": "Scrypt",
        "links": [
            {
                "section": [
                    "Main",
                    "Apps"
                ],
                "name": "web site",
                "url": null,
                "icon": "website.png"
            },
            {
                "section": [
                    "Main",
                    "Code"
                ],
                "name": "github",
                "url": "https://github.com/geocoin/geocoin",
                "icon": "github.png"
            }
        ],
        "rating": 0
    },
    "aliases": {
        "CoinMarketCap": "GeoCoin",
        "CurrencyName": "GeoCoin"
    }
}