{
    "name": "MetalCoin",
    "symbol": "METAL",
    "source": "cyberFund",
    "metrics": {
        "announce": "27/11/2014",
        "genesis": null,
        "status": "Running",
        "p2p": null,
        "rpc": null,
        "blockTime": "90 seconds",
        "reward": "Block 2-100:0 METAL, Block 101-2500:5000 METAL, Block 2501-5000:4500 METAL, Block 5001-7500:4000 METAL, Block 7501-10000:3500 METAL, Block 10001-12500:3000 METAL, Block 12501-15000:2500 METAL, Block 15001-17500:2000 METAL, Block 17501-20000:1500 METAL, Block 20001-22500:1000 METAL, Block 22501-50000:666 METAL",
        "total": "91315000 Metal",
        "premine": "1000000 METAL",
        "difficultyCycle": "every block",
        "txsConfirm": null,
        "mintConfirm": null,
        "ann": "https://bitcointalk.org/index.php?topic=886655",
        "algo": "X11",
        "links": [
            {
                "section": [
                    "Main",
                    "Apps"
                ],
                "name": "web site",
                "url": null,
                "icon": "website.png"
            },
            {
                "section": [
                    "Main",
                    "Code"
                ],
                "name": "github",
                "url": "https://github.com/MetalCoinTeam/MetalCoin",
                "icon": "github.png"
            }
        ],
        "rating": 0
    },
    "aliases": {
        "CoinMarketCap": "MetalCoin",
        "CurrencyName": "MetalCoin"
    }
}