{
    "name": "Xmascoin",
    "symbol": "XMAS",
    "source": "cyberFund",
    "metrics": {
        "announce": "29/12/2013",
        "genesis": null,
        "status": "Dead",
        "p2p": 9366,
        "rpc": 9365,
        "blockTime": 600,
        "reward": 365,
        "halfingCycle": null,
        "total": 95922000,
        "premine": null,
        "difficultyCycle": 1,
        "txsConfirm": null,
        "mintConfirm": null,
        "ann": "https://bitcointalk.org/index.php?topic=390020.0",
        "algo": "Scrypt",
        "links": [
            {
                "section": [
                    "Main",
                    "Apps"
                ],
                "name": "web site",
                "url": null,
                "icon": "website.png"
            },
            {
                "section": [
                    "Main",
                    "Code"
                ],
                "name": "github",
                "url": "https://github.com/XmasCoin/XmasCoin.git",
                "icon": "github.png"
            }
        ]
    },
    "aliases": {
        "CoinMarketCap": "Xmascoin",
        "CurrencyName": "Xmascoin"
    }
}