{
    "name": "Cthulhu Offerings",
    "symbol": "OFF",
    "source": "cyberFund",
    "metrics": {
        "announce": "14/09/2013",
        "genesis": null,
        "status": "Running",
        "p2p": 20000,
        "rpc": 1928,
        "blockTime": "60",
        "reward": 5,
        "halfingCycle": "every 6 months",
        "total": null,
        "premine": "10000 () for bounties",
        "difficultyCycle": "20",
        "txsConfirm": 30,
        "mintConfirm": null,
        "ann": "https://bitcointalk.org/index.php?topic=294383.0",
        "algo": "Quark",
        "links": [
            {
                "section": [
                    "Main",
                    "Apps"
                ],
                "name": "web site",
                "url": "http://cthulhu.tk/",
                "icon": "website.png"
            },
            {
                "section": [
                    "Main",
                    "Code"
                ],
                "name": "github",
                "url": "https://github.com/thegreatoldone/offerings",
                "icon": "github.png"
            }
        ]
    },
    "aliases": {
        "CoinMarketCap": "Cthulhu Offerings",
        "CurrencyName": "Cthulhu Offerings"
    }
}