{
    "name": "BitLion",
    "symbol": "XBL",
    "source": "cyberFund",
    "metrics": {
        "announce": "21/06/2014",
        "genesis": "18/06/2014",
        "status": "Dead",
        "p2p": 9977,
        "rpc": 9980,
        "blockTime": "PoW: 90; PoS: 210",
        "reward": "Reward PoW: depends on the complexity of the network PoW, a maximum of 32 coins. Reward PoS: depends on the complexity of the network PoS, a maximum of 32 coins",
        "halfingCycle": null,
        "total": 100000000,
        "premine": "200000 (0.2%)  - mainly bounty",
        "difficultyCycle": null,
        "txsConfirm": null,
        "mintConfirm": null,
        "ann": "https://bitcointalk.org/index.php?topic=660737.0",
        "algo": "X-n",
        "links": [
            {
                "section": [
                    "Main",
                    "Apps"
                ],
                "name": "web site",
                "url": "http://bitlion.org/",
                "icon": "website.png"
            },
            {
                "section": [
                    "Main",
                    "Code"
                ],
                "name": "github",
                "url": "https://github.com/lemial/bitlion",
                "icon": "github.png"
            }
        ]
    },
    "aliases": {
        "CoinMarketCap": "BitLion",
        "CurrencyName": "BitLion"
    }
}