{
    "name": "FourOhFourCoin",
    "symbol": "FOF",
    "source": "cyberFund",
    "metrics": {
        "announce": "14/03/2014",
        "genesis": null,
        "status": "Dead",
        "p2p": null,
        "rpc": null,
        "blockTime": 60,
        "reward": "404 (or 0, or 808)",
        "halfingCycle": null,
        "total": 1000000000,
        "premine": null,
        "difficultyCycle": "",
        "txsConfirm": null,
        "mintConfirm": null,
        "ann": "https://bitcointalk.org/index.php?topic=515642.0",
        "algo": "Scrypt",
        "links": [
            {
                "section": [
                    "Main",
                    "Apps"
                ],
                "name": "web site",
                "url": "http://fourohfourcoin.com",
                "icon": "website.png"
            },
            {
                "section": [
                    "Main",
                    "Code"
                ],
                "name": "github",
                "url": "https://github.com/CoinNotFound/FourOhFourCoin",
                "icon": "github.png"
            }
        ]
    },
    "aliases": {
        "CoinMarketCap": "FourOhFourCoin",
        "CurrencyName": "FourOhFourCoin"
    }
}